Workbook

Sheet Stop Loss Companies
A1: # | B1: Company | C1: Category | D1: Parent / Paper | E1: HQ | F1: What they do | G1: Confidence | H1: Outreach status | I1: Notes
A2: 1 | B2: Cigna Healthcare | C2: Carrier - national health plan | D2: The Cigna Group | E2: Bloomfield, CT | F2: Largest stop-loss writer in the US (~$8B annual premium). Sold mainly alongside Cigna ASO. Margin repricing expected to run through 2027. | G2: Verified in 2026 search
A3: 2 | B3: UnitedHealthcare | C3: Carrier - national health plan | D3: UnitedHealth Group | E3: Minnetonka, MN | F3: Stop loss for ASO and level-funded (All Savers) employers. | G3: Verified in 2026 search
A4: 3 | B4: Aetna | C4: Carrier - national health plan | D4: CVS Health | E4: Hartford, CT | F4: Stop loss for Aetna self-funded and level-funded (Aetna Funding Advantage) clients. | G4: Verified in 2026 search
A5: 4 | B5: Anthem Stop Loss | C5: Carrier - Blue plan | D5: Elevance Health | E5: Indianapolis, IN | F5: Stop loss for Anthem ASO and level-funded clients. SIIA member. | G5: Verified in 2026 search
A6: 5 | B6: Wellpoint | C6: Carrier - health plan | D6: Elevance Health | E6: Indianapolis, IN | F6: Elevance brand in non-Blue states. Listed among stop-loss providers. | G6: Verified in 2026 search
A7: 6 | B7: Sun Life U.S. | C7: Carrier - independent | D7: Sun Life Financial | E7: Wellesley Hills, MA | F7: Largest independent (non-health-plan) stop-loss carrier. Also runs captive programs and the Health Navigator high-cost claimant (HCC) program. | G7: Verified in 2026 search
A8: 7 | B8: Voya Employee Benefits | C8: Carrier - independent | D8: Voya Financial | E8: Minneapolis, MN | F8: Top-10 stop-loss writer by in-force premium; most policies renew Jan 1. Also offers group captive programs. | G8: Verified in 2026 search
A9: 8 | B9: Symetra | C9: Carrier - independent | D9: Symetra Financial (Sumitomo Life) | E9: Bellevue, WA | F9: Large independent medical stop-loss writer, sold through brokers and TPAs. | G9: From prior knowledge - verify
A10: 9 | B10: Tokio Marine HCC - Stop Loss Group | C10: Carrier - specialty | D10: Tokio Marine HCC (HCC Life Insurance Co.) | E10: Kennesaw, GA | F10: Major specialty stop-loss and organ-transplant writer. Also issues paper for MGUs (e.g., RSL). | G10: Verified in 2026 search
A11: 10 | B11: HM Insurance Group | C11: Carrier - specialty | D11: Highmark Health | E11: Pittsburgh, PA | F11: National stop-loss carrier owned by Highmark; also managed care reinsurance. | G11: Verified in 2026 search
A12: 11 | B12: Berkley Accident and Health | C12: Carrier - specialty | D12: W. R. Berkley | E12: Hamilton Square, NJ | F12: Stop loss, group captives (Berkley Fusion), and managed care reinsurance. | G12: Verified in 2026 search
A13: 12 | B13: Berkshire Hathaway Specialty Insurance (BHSI) | C13: Carrier - specialty | D13: Berkshire Hathaway | E13: Boston, MA | F13: Medical stop loss for self-funded employers. | G13: Verified in 2026 search
... A76: 75 | B76: Munich Re (US Health) | C76: Reinsurer | D76: Munich Re | E76: Princeton, NJ | F76: Reinsures US medical stop loss. | G76: From prior knowledge - verify

Sheet Summary
A1: Category | B1: Count
A2: Carrier - national health plan | B2: =COUNTIF('Stop Loss Companies'!$C$2:$C$76,A2) -> 3
A3: Carrier - Blue plan | B3: =COUNTIF('Stop Loss Companies'!$C$2:$C$76,A3) -> 6
A4: Carrier - health plan | B4: =COUNTIF('Stop Loss Companies'!$C$2:$C$76,A4) -> 1
A5: Carrier - independent | B5: =COUNTIF('Stop Loss Companies'!$C$2:$C$76,A5) -> 4
A6: Carrier - specialty | B6: =COUNTIF('Stop Loss Companies'!$C$2:$C$76,A6) -> 11
A7: Carrier - specialty / reinsurer | B7: =COUNTIF('Stop Loss Companies'!$C$2:$C$76,A7) -> 1
A8: Carrier - writes through MGUs | B8: =COUNTIF('Stop Loss Companies'!$C$2:$C$76,A8) -> 4
A9: Carrier - Blue affiliate | B9: =COUNTIF('Stop Loss Companies'!$C$2:$C$76,A9) -> 1
A10: Carrier | B10: =COUNTIF('Stop Loss Companies'!$C$2:$C$76,A10) -> 3
A11: Carrier - Blues-owned | B11: =COUNTIF('Stop Loss Companies'!$C$2:$C$76,A11) -> 1
A12: Carrier - fronting/paper | B12: =COUNTIF('Stop Loss Companies'!$C$2:$C$76,A12) -> 2
A13: MGU / general agency | B13: =COUNTIF('Stop Loss Companies'!$C$2:$C$76,A13) -> 1
... A22: Reinsurer | B22: =COUNTIF('Stop Loss Companies'!$C$2:$C$76,A22) -> 3
A23: Total | B23: =SUM(B2:B22) -> 75
A25: Verified in 2026 search | B25: =COUNTIF('Stop Loss Companies'!$G$2:$G$76,A25) -> 50
A26: From prior knowledge - verify | B26: =COUNTIF('Stop Loss Companies'!$G$2:$G$76,A26) -> 25
A28: How to use this list
A29: Yellow columns (Outreach status, Notes) are yours to fill in, e.g. 'Researching', 'Contacted', 'Meeting set'.
A30: Confidence: 'Verified' means a 2026 web search confirmed the company is in medical stop loss. Orange 'verify' rows come from prior knowledge or older directories; confirm before outreach.
A31: HQ shown as '--' where it was not confirmed.
A32: Market context: US medical stop-loss premium was roughly $36-40B in 2024 (Oliver Wyman/Guy Carpenter; Milliman). National health plans, Blues and large direct writers hold about 80% of it.
A33: Why this matters for VIVIO: high-cost claimants are heavily specialty drug and gene therapy. Specialty drug management lowers stop-loss claims and renewal pricing, so carriers, MGUs and captives are channel partners and referral sources to self-insured employers, not just a list of names.
A35: Sources
A36: Jencap A&H consolidation (2026): https://www.theinsurer.com/program-manager/news/jencap-combines-stop-loss-mgus-under-new-ah-brand-2026-07-01/
A37: Sands Point / BRM (2025): https://www.reinsurancene.ws/sands-point-risk-acquires-medical-stop-loss-mgu-brm-specialty-markets/
A38: Nationwide MGU partners: https://news.nationwide.com/nationwide-grows-medical-stop-loss-capabilities/
A39: Zurich / IOA Re: https://www.theinsurer.com/ti/news/zurich-na-agrees-capacity-deal-with-medical-stop-loss-mgu-ioa-re/
A40: Crum & Forster / Partners MGU: https://www.cfins.com/crum-forster-accident-health-division-announces-acquisition-of-partners-mgu/
... A49: Litchfield, MLB RE, USBenefits: https://www.litchfieldrisk.com/ , https://mlbre.com/ , https://www.usbstoploss.com/
